[{"verse_number":29,"verse_key":"48:29","text_imlaei_simple":"محمد رسول الله والذين معه اشداء على الكفار رحماء بينهم تراهم ركعا سجدا يبتغون فضلا من الله ورضوانا سيماهم في وجوههم من اثر السجود ذلك مثلهم في التوراة ومثلهم في الانجيل كزرع اخرج شطاه فازره فاستغلظ فاستوى على سوقه يعجب الزراع ليغيظ بهم الكفار وعد الله الذين امنوا وعملوا الصالحات منهم مغفرة واجرا عظيما","page_number":515,"juz_number":26,"words":["ﭑ","ﭒ","ﭓﭔ","ﭕ","ﭖ","ﭗ","ﭘ","ﭙ","ﭚ","ﭛﭜ","ﭝ","ﭞ","ﭟ","ﭠ","ﭡ","ﭢ","ﭣ","ﭤﭥ","ﭦ","ﭧ","ﭨ","ﭩ","ﭪ","ﭫﭬ","ﭭ","ﭮ","ﭯ","ﭰﭱ","ﭲ","ﭳ","ﭴ","ﭵ","ﭶ","ﭷ","ﭸ","ﭹ","ﭺ","ﭻ","ﭼ","ﭽ","ﭾ","ﭿ","ﮀ","ﮁﮂ","ﮃ","ﮄ","ﮅ","ﮆ","ﮇ","ﮈ","ﮉ","ﮊ","ﮋ","ﮌ","ﮍ"]},{"verse_number":1,"verse_key":"49:1","text_imlaei_simple":"يا ايها الذين امنوا لا تقدموا بين يدي الله ورسوله واتقوا الله ان الله سميع عليم","page_number":515,"juz_number":26,"words":["ﮎ","ﮏ","ﮐ","ﮑ","ﮒ","ﮓ","ﮔ","ﮕ","ﮖﮗ","ﮘ","ﮙﮚ","ﮛ","ﮜ","ﮝ","ﮞ","ﮟ"]},{"verse_number":2,"verse_key":"49:2","text_imlaei_simple":"يا ايها الذين امنوا لا ترفعوا اصواتكم فوق صوت النبي ولا تجهروا له بالقول كجهر بعضكم لبعض ان تحبط اعمالكم وانتم لا تشعرون","page_number":515,"juz_number":26,"words":["ﮠ","ﮡ","ﮢ","ﮣ","ﮤ","ﮥ","ﮦ","ﮧ","ﮨ","ﮩ","ﮪ","ﮫ","ﮬ","ﮭ","ﮮ","ﮯ","ﮰ","ﮱ","ﯓ","ﯔ","ﯕ","ﯖ","ﯗ"]},{"verse_number":3,"verse_key":"49:3","text_imlaei_simple":"ان الذين يغضون اصواتهم عند رسول الله اولئك الذين امتحن الله قلوبهم للتقوى لهم مغفرة واجر عظيم","page_number":515,"juz_number":26,"words":["ﯘ","ﯙ","ﯚ","ﯛ","ﯜ","ﯝ","ﯞ","ﯟ","ﯠ","ﯡ","ﯢ","ﯣ","ﯤﯥ","ﯦ","ﯧ","ﯨ","ﯩ","ﯪ"]},{"verse_number":4,"verse_key":"49:4","text_imlaei_simple":"ان الذين ينادونك من وراء الحجرات اكثرهم لا يعقلون","page_number":515,"juz_number":26,"words":["ﯫ","ﯬ","ﯭ","ﯮ","ﯯ","ﯰ","ﯱ","ﯲ","ﯳ","ﯴ"]}]