[{"verse_number":12,"verse_key":"4:12","text_imlaei_simple":"ولكم نصف ما ترك ازواجكم ان لم يكن لهن ولد فان كان لهن ولد فلكم الربع مما تركن من بعد وصية يوصين بها او دين ولهن الربع مما تركتم ان لم يكن لكم ولد فان كان لكم ولد فلهن الثمن مما تركتم من بعد وصية توصون بها او دين وان كان رجل يورث كلالة او امراة وله اخ او اخت فلكل واحد منهما السدس فان كانوا اكثر من ذلك فهم شركاء في الثلث من بعد وصية يوصى بها او دين غير مضار وصية من الله والله عليم حليم","page_number":79,"juz_number":4,"words":["ﭑ ﭒ","ﭓ","ﭔ","ﭕ","ﭖ","ﭗ","ﭘ","ﭙ","ﭚ","ﭛﭜ","ﭝ","ﭞ","ﭟ","ﭠ","ﭡ","ﭢ","ﭣ","ﭤﭥ","ﭦ","ﭧ","ﭨ","ﭩ","ﭪ","ﭫ","ﭬﭭ","ﭮ","ﭯ","ﭰ","ﭱ","ﭲ","ﭳ","ﭴ","ﭵ","ﭶﭷ","ﭸ","ﭹ","ﭺ","ﭻ","ﭼ","ﭽ","ﭾ","ﭿﮀ","ﮁ","ﮂ","ﮃ","ﮄ","ﮅ","ﮆ","ﮇﮈ","ﮉ","ﮊ","ﮋ","ﮌ","ﮍ","ﮎ","ﮏ","ﮐ","ﮑ","ﮒ","ﮓ","ﮔ","ﮕ","ﮖ","ﮗﮘ","ﮙ","ﮚ","ﮛ","ﮜ","ﮝ","ﮞ","ﮟ","ﮠ","ﮡﮢ","ﮣ","ﮤ","ﮥ","ﮦ","ﮧ","ﮨ","ﮩ","ﮪ","ﮫﮬ","ﮭ","ﮮ","ﮯﮰ","ﮱ","ﯓ","ﯔ","ﯕ"]},{"verse_number":13,"verse_key":"4:13","text_imlaei_simple":"تلك حدود الله ومن يطع الله ورسوله يدخله جنات تجري من تحتها الانهار خالدين فيها وذلك الفوز العظيم","page_number":79,"juz_number":4,"words":["ﯖ","ﯗ","ﯘﯙ","ﯚ","ﯛ","ﯜ","ﯝ","ﯞ","ﯟ","ﯠ","ﯡ","ﯢ","ﯣ","ﯤ","ﯥﯦ","ﯧ","ﯨ","ﯩ","ﯪ"]},{"verse_number":14,"verse_key":"4:14","text_imlaei_simple":"ومن يعص الله ورسوله ويتعد حدوده يدخله نارا خالدا فيها وله عذاب مهين","page_number":79,"juz_number":4,"words":["ﯫ","ﯬ","ﯭ","ﯮ","ﯯ","ﯰ","ﯱ","ﯲ","ﯳ","ﯴ","ﯵ","ﯶ","ﯷ","ﯸ"]}]