[{"id":4373,"verse_number":48,"verse_key":"43:48","hizb_number":50,"rub_el_hizb_number":197,"ruku_number":430,"manzil_number":6,"sajdah_number":null,"text_imlaei_simple":"وما نريهم من اية الا هي اكبر من اختها واخذناهم بالعذاب لعلهم يرجعون","page_number":493,"juz_number":25,"words":[{"id":47073,"position":1,"audio_url":"wbw/043_048_001.mp3","verse_key":"43:48","verse_id":4373,"location":"43:48:1","code_v1":"ﭑ","char_type_name":"word","page_number":493,"line_number":1,"text":"ﭑ"},{"id":47074,"position":2,"audio_url":"wbw/043_048_002.mp3","verse_key":"43:48","verse_id":4373,"location":"43:48:2","code_v1":"ﭒ","char_type_name":"word","page_number":493,"line_number":1,"text":"ﭒ"},{"id":47075,"position":3,"audio_url":"wbw/043_048_003.mp3","verse_key":"43:48","verse_id":4373,"location":"43:48:3","code_v1":"ﭓ","char_type_name":"word","page_number":493,"line_number":1,"text":"ﭓ"},{"id":47076,"position":4,"audio_url":"wbw/043_048_004.mp3","verse_key":"43:48","verse_id":4373,"location":"43:48:4","code_v1":"ﭔ","char_type_name":"word","page_number":493,"line_number":1,"text":"ﭔ"},{"id":47077,"position":5,"audio_url":"wbw/043_048_005.mp3","verse_key":"43:48","verse_id":4373,"location":"43:48:5","code_v1":"ﭕ","char_type_name":"word","page_number":493,"line_number":1,"text":"ﭕ"},{"id":47078,"position":6,"audio_url":"wbw/043_048_006.mp3","verse_key":"43:48","verse_id":4373,"location":"43:48:6","code_v1":"ﭖ","char_type_name":"word","page_number":493,"line_number":1,"text":"ﭖ"},{"id":47079,"position":7,"audio_url":"wbw/043_048_007.mp3","verse_key":"43:48","verse_id":4373,"location":"43:48:7","code_v1":"ﭗ","char_type_name":"word","page_number":493,"line_number":1,"text":"ﭗ"},{"id":47080,"position":8,"audio_url":"wbw/043_048_008.mp3","verse_key":"43:48","verse_id":4373,"location":"43:48:8","code_v1":"ﭘ","char_type_name":"word","page_number":493,"line_number":1,"text":"ﭘ"},{"id":47081,"position":9,"audio_url":"wbw/043_048_009.mp3","verse_key":"43:48","verse_id":4373,"location":"43:48:9","code_v1":"ﭙﭚ","char_type_name":"word","page_number":493,"line_number":1,"text":"ﭙﭚ"},{"id":47083,"position":10,"audio_url":"wbw/043_048_011.mp3","verse_key":"43:48","verse_id":4373,"location":"43:48:10","code_v1":"ﭛ","char_type_name":"word","page_number":493,"line_number":1,"text":"ﭛ"},{"id":47084,"position":11,"audio_url":"wbw/043_048_012.mp3","verse_key":"43:48","verse_id":4373,"location":"43:48:11","code_v1":"ﭜ","char_type_name":"word","page_number":493,"line_number":2,"text":"ﭜ"},{"id":47085,"position":12,"audio_url":"wbw/043_048_013.mp3","verse_key":"43:48","verse_id":4373,"location":"43:48:12","code_v1":"ﭝ","char_type_name":"word","page_number":493,"line_number":2,"text":"ﭝ"},{"id":47086,"position":13,"audio_url":"wbw/043_048_014.mp3","verse_key":"43:48","verse_id":4373,"location":"43:48:13","code_v1":"ﭞ","char_type_name":"word","page_number":493,"line_number":2,"text":"ﭞ"},{"id":47087,"position":14,"audio_url":null,"verse_key":"43:48","verse_id":4373,"location":"43:48:14","code_v1":"ﭟ","char_type_name":"end","page_number":493,"line_number":2,"text":"ﭟ"}]}, {"id":4374,"verse_number":49,"verse_key":"43:49","hizb_number":50,"rub_el_hizb_number":197,"ruku_number":430,"manzil_number":6,"sajdah_number":null,"text_imlaei_simple":"وقالوا يا ايه الساحر ادع لنا ربك بما عهد عندك اننا لمهتدون","page_number":493,"juz_number":25,"words":[{"id":47789,"position":1,"audio_url":"wbw/043_049_001.mp3","verse_key":"43:49","verse_id":4374,"location":"43:49:1","code_v1":"ﭠ","char_type_name":"word","page_number":493,"line_number":2,"text":"ﭠ"},{"id":47790,"position":2,"audio_url":"wbw/043_049_002.mp3","verse_key":"43:49","verse_id":4374,"location":"43:49:2","code_v1":"ﭡ","char_type_name":"word","page_number":493,"line_number":2,"text":"ﭡ"},{"id":47791,"position":3,"audio_url":"wbw/043_049_003.mp3","verse_key":"43:49","verse_id":4374,"location":"43:49:3","code_v1":"ﭢ","char_type_name":"word","page_number":493,"line_number":2,"text":"ﭢ"},{"id":47792,"position":4,"audio_url":"wbw/043_049_004.mp3","verse_key":"43:49","verse_id":4374,"location":"43:49:4","code_v1":"ﭣ","char_type_name":"word","page_number":493,"line_number":2,"text":"ﭣ"},{"id":47793,"position":5,"audio_url":"wbw/043_049_005.mp3","verse_key":"43:49","verse_id":4374,"location":"43:49:5","code_v1":"ﭤ","char_type_name":"word","page_number":493,"line_number":2,"text":"ﭤ"},{"id":47794,"position":6,"audio_url":"wbw/043_049_006.mp3","verse_key":"43:49","verse_id":4374,"location":"43:49:6","code_v1":"ﭥ","char_type_name":"word","page_number":493,"line_number":3,"text":"ﭥ"},{"id":47795,"position":7,"audio_url":"wbw/043_049_007.mp3","verse_key":"43:49","verse_id":4374,"location":"43:49:7","code_v1":"ﭦ","char_type_name":"word","page_number":493,"line_number":3,"text":"ﭦ"},{"id":47796,"position":8,"audio_url":"wbw/043_049_008.mp3","verse_key":"43:49","verse_id":4374,"location":"43:49:8","code_v1":"ﭧ","char_type_name":"word","page_number":493,"line_number":3,"text":"ﭧ"},{"id":47797,"position":9,"audio_url":"wbw/043_049_009.mp3","verse_key":"43:49","verse_id":4374,"location":"43:49:9","code_v1":"ﭨ","char_type_name":"word","page_number":493,"line_number":3,"text":"ﭨ"},{"id":47798,"position":10,"audio_url":"wbw/043_049_010.mp3","verse_key":"43:49","verse_id":4374,"location":"43:49:10","code_v1":"ﭩ","char_type_name":"word","page_number":493,"line_number":3,"text":"ﭩ"},{"id":47799,"position":11,"audio_url":"wbw/043_049_011.mp3","verse_key":"43:49","verse_id":4374,"location":"43:49:11","code_v1":"ﭪ","char_type_name":"word","page_number":493,"line_number":3,"text":"ﭪ"},{"id":47800,"position":12,"audio_url":null,"verse_key":"43:49","verse_id":4374,"location":"43:49:12","code_v1":"ﭫ","char_type_name":"end","page_number":493,"line_number":3,"text":"ﭫ"}]}, {"id":4375,"verse_number":50,"verse_key":"43:50","hizb_number":50,"rub_el_hizb_number":197,"ruku_number":430,"manzil_number":6,"sajdah_number":null,"text_imlaei_simple":"فلما كشفنا عنهم العذاب اذا هم ينكثون","page_number":493,"juz_number":25,"words":[{"id":48679,"position":1,"audio_url":"wbw/043_050_001.mp3","verse_key":"43:50","verse_id":4375,"location":"43:50:1","code_v1":"ﭬ","char_type_name":"word","page_number":493,"line_number":3,"text":"ﭬ"},{"id":48680,"position":2,"audio_url":"wbw/043_050_002.mp3","verse_key":"43:50","verse_id":4375,"location":"43:50:2","code_v1":"ﭭ","char_type_name":"word","page_number":493,"line_number":3,"text":"ﭭ"},{"id":48681,"position":3,"audio_url":"wbw/043_050_003.mp3","verse_key":"43:50","verse_id":4375,"location":"43:50:3","code_v1":"ﭮ","char_type_name":"word","page_number":493,"line_number":3,"text":"ﭮ"},{"id":48682,"position":4,"audio_url":"wbw/043_050_004.mp3","verse_key":"43:50","verse_id":4375,"location":"43:50:4","code_v1":"ﭯ","char_type_name":"word","page_number":493,"line_number":4,"text":"ﭯ"},{"id":48683,"position":5,"audio_url":"wbw/043_050_005.mp3","verse_key":"43:50","verse_id":4375,"location":"43:50:5","code_v1":"ﭰ","char_type_name":"word","page_number":493,"line_number":4,"text":"ﭰ"},{"id":48684,"position":6,"audio_url":"wbw/043_050_006.mp3","verse_key":"43:50","verse_id":4375,"location":"43:50:6","code_v1":"ﭱ","char_type_name":"word","page_number":493,"line_number":4,"text":"ﭱ"},{"id":48685,"position":7,"audio_url":"wbw/043_050_007.mp3","verse_key":"43:50","verse_id":4375,"location":"43:50:7","code_v1":"ﭲ","char_type_name":"word","page_number":493,"line_number":4,"text":"ﭲ"},{"id":48686,"position":8,"audio_url":null,"verse_key":"43:50","verse_id":4375,"location":"43:50:8","code_v1":"ﭳ","char_type_name":"end","page_number":493,"line_number":4,"text":"ﭳ"}]}, {"id":4376,"verse_number":51,"verse_key":"43:51","hizb_number":50,"rub_el_hizb_number":197,"ruku_number":430,"manzil_number":6,"sajdah_number":null,"text_imlaei_simple":"ونادى فرعون في قومه قال يا قوم اليس لي ملك مصر وهذه الانهار تجري من تحتي افلا تبصرون","page_number":493,"juz_number":25,"words":[{"id":49080,"position":1,"audio_url":"wbw/043_051_001.mp3","verse_key":"43:51","verse_id":4376,"location":"43:51:1","code_v1":"ﭴ","char_type_name":"word","page_number":493,"line_number":4,"text":"ﭴ"},{"id":49081,"position":2,"audio_url":"wbw/043_051_002.mp3","verse_key":"43:51","verse_id":4376,"location":"43:51:2","code_v1":"ﭵ","char_type_name":"word","page_number":493,"line_number":4,"text":"ﭵ"},{"id":49082,"position":3,"audio_url":"wbw/043_051_003.mp3","verse_key":"43:51","verse_id":4376,"location":"43:51:3","code_v1":"ﭶ","char_type_name":"word","page_number":493,"line_number":4,"text":"ﭶ"},{"id":49083,"position":4,"audio_url":"wbw/043_051_004.mp3","verse_key":"43:51","verse_id":4376,"location":"43:51:4","code_v1":"ﭷ","char_type_name":"word","page_number":493,"line_number":4,"text":"ﭷ"},{"id":49084,"position":5,"audio_url":"wbw/043_051_005.mp3","verse_key":"43:51","verse_id":4376,"location":"43:51:5","code_v1":"ﭸ","char_type_name":"word","page_number":493,"line_number":5,"text":"ﭸ"},{"id":49085,"position":6,"audio_url":"wbw/043_051_006.mp3","verse_key":"43:51","verse_id":4376,"location":"43:51:6","code_v1":"ﭹ","char_type_name":"word","page_number":493,"line_number":5,"text":"ﭹ"},{"id":49086,"position":7,"audio_url":"wbw/043_051_007.mp3","verse_key":"43:51","verse_id":4376,"location":"43:51:7","code_v1":"ﭺ","char_type_name":"word","page_number":493,"line_number":5,"text":"ﭺ"},{"id":49087,"position":8,"audio_url":"wbw/043_051_008.mp3","verse_key":"43:51","verse_id":4376,"location":"43:51:8","code_v1":"ﭻ","char_type_name":"word","page_number":493,"line_number":5,"text":"ﭻ"},{"id":49088,"position":9,"audio_url":"wbw/043_051_009.mp3","verse_key":"43:51","verse_id":4376,"location":"43:51:9","code_v1":"ﭼ","char_type_name":"word","page_number":493,"line_number":5,"text":"ﭼ"},{"id":49089,"position":10,"audio_url":"wbw/043_051_010.mp3","verse_key":"43:51","verse_id":4376,"location":"43:51:10","code_v1":"ﭽ","char_type_name":"word","page_number":493,"line_number":5,"text":"ﭽ"},{"id":49090,"position":11,"audio_url":"wbw/043_051_011.mp3","verse_key":"43:51","verse_id":4376,"location":"43:51:11","code_v1":"ﭾ","char_type_name":"word","page_number":493,"line_number":5,"text":"ﭾ"},{"id":49091,"position":12,"audio_url":"wbw/043_051_012.mp3","verse_key":"43:51","verse_id":4376,"location":"43:51:12","code_v1":"ﭿ","char_type_name":"word","page_number":493,"line_number":5,"text":"ﭿ"},{"id":49092,"position":13,"audio_url":"wbw/043_051_013.mp3","verse_key":"43:51","verse_id":4376,"location":"43:51:13","code_v1":"ﮀ","char_type_name":"word","page_number":493,"line_number":5,"text":"ﮀ"},{"id":49093,"position":14,"audio_url":"wbw/043_051_014.mp3","verse_key":"43:51","verse_id":4376,"location":"43:51:14","code_v1":"ﮁ","char_type_name":"word","page_number":493,"line_number":5,"text":"ﮁ"},{"id":49094,"position":15,"audio_url":"wbw/043_051_015.mp3","verse_key":"43:51","verse_id":4376,"location":"43:51:15","code_v1":"ﮂﮃ","char_type_name":"word","page_number":493,"line_number":6,"text":"ﮂﮃ"},{"id":49096,"position":16,"audio_url":"wbw/043_051_017.mp3","verse_key":"43:51","verse_id":4376,"location":"43:51:16","code_v1":"ﮄ","char_type_name":"word","page_number":493,"line_number":6,"text":"ﮄ"},{"id":49097,"position":17,"audio_url":"wbw/043_051_018.mp3","verse_key":"43:51","verse_id":4376,"location":"43:51:17","code_v1":"ﮅ","char_type_name":"word","page_number":493,"line_number":6,"text":"ﮅ"},{"id":49098,"position":18,"audio_url":null,"verse_key":"43:51","verse_id":4376,"location":"43:51:18","code_v1":"ﮆ","char_type_name":"end","page_number":493,"line_number":6,"text":"ﮆ"}]}, {"id":4377,"verse_number":52,"verse_key":"43:52","hizb_number":50,"rub_el_hizb_number":197,"ruku_number":430,"manzil_number":6,"sajdah_number":null,"text_imlaei_simple":"ام انا خير من هذا الذي هو مهين ولا يكاد يبين","page_number":493,"juz_number":25,"words":[{"id":49808,"position":1,"audio_url":"wbw/043_052_001.mp3","verse_key":"43:52","verse_id":4377,"location":"43:52:1","code_v1":"ﮇ","char_type_name":"word","page_number":493,"line_number":6,"text":"ﮇ"},{"id":49809,"position":2,"audio_url":"wbw/043_052_002.mp3","verse_key":"43:52","verse_id":4377,"location":"43:52:2","code_v1":"ﮈ","char_type_name":"word","page_number":493,"line_number":6,"text":"ﮈ"},{"id":49810,"position":3,"audio_url":"wbw/043_052_003.mp3","verse_key":"43:52","verse_id":4377,"location":"43:52:3","code_v1":"ﮉ","char_type_name":"word","page_number":493,"line_number":6,"text":"ﮉ"},{"id":49811,"position":4,"audio_url":"wbw/043_052_004.mp3","verse_key":"43:52","verse_id":4377,"location":"43:52:4","code_v1":"ﮊ","char_type_name":"word","page_number":493,"line_number":6,"text":"ﮊ"},{"id":49812,"position":5,"audio_url":"wbw/043_052_005.mp3","verse_key":"43:52","verse_id":4377,"location":"43:52:5","code_v1":"ﮋ","char_type_name":"word","page_number":493,"line_number":6,"text":"ﮋ"},{"id":49813,"position":6,"audio_url":"wbw/043_052_006.mp3","verse_key":"43:52","verse_id":4377,"location":"43:52:6","code_v1":"ﮌ","char_type_name":"word","page_number":493,"line_number":6,"text":"ﮌ"},{"id":49814,"position":7,"audio_url":"wbw/043_052_007.mp3","verse_key":"43:52","verse_id":4377,"location":"43:52:7","code_v1":"ﮍ","char_type_name":"word","page_number":493,"line_number":6,"text":"ﮍ"},{"id":49815,"position":8,"audio_url":"wbw/043_052_008.mp3","verse_key":"43:52","verse_id":4377,"location":"43:52:8","code_v1":"ﮎ","char_type_name":"word","page_number":493,"line_number":6,"text":"ﮎ"},{"id":49816,"position":9,"audio_url":"wbw/043_052_009.mp3","verse_key":"43:52","verse_id":4377,"location":"43:52:9","code_v1":"ﮏ","char_type_name":"word","page_number":493,"line_number":7,"text":"ﮏ"},{"id":49817,"position":10,"audio_url":"wbw/043_052_010.mp3","verse_key":"43:52","verse_id":4377,"location":"43:52:10","code_v1":"ﮐ","char_type_name":"word","page_number":493,"line_number":7,"text":"ﮐ"},{"id":49818,"position":11,"audio_url":"wbw/043_052_011.mp3","verse_key":"43:52","verse_id":4377,"location":"43:52:11","code_v1":"ﮑ","char_type_name":"word","page_number":493,"line_number":7,"text":"ﮑ"},{"id":49819,"position":12,"audio_url":null,"verse_key":"43:52","verse_id":4377,"location":"43:52:12","code_v1":"ﮒ","char_type_name":"end","page_number":493,"line_number":7,"text":"ﮒ"}]}, {"id":4378,"verse_number":53,"verse_key":"43:53","hizb_number":50,"rub_el_hizb_number":197,"ruku_number":430,"manzil_number":6,"sajdah_number":null,"text_imlaei_simple":"فلولا القي عليه اسورة من ذهب او جاء معه الملائكة مقترنين","page_number":493,"juz_number":25,"words":[{"id":50415,"position":1,"audio_url":"wbw/043_053_001.mp3","verse_key":"43:53","verse_id":4378,"location":"43:53:1","code_v1":"ﮓ","char_type_name":"word","page_number":493,"line_number":7,"text":"ﮓ"},{"id":50416,"position":2,"audio_url":"wbw/043_053_002.mp3","verse_key":"43:53","verse_id":4378,"location":"43:53:2","code_v1":"ﮔ","char_type_name":"word","page_number":493,"line_number":7,"text":"ﮔ"},{"id":50417,"position":3,"audio_url":"wbw/043_053_003.mp3","verse_key":"43:53","verse_id":4378,"location":"43:53:3","code_v1":"ﮕ","char_type_name":"word","page_number":493,"line_number":7,"text":"ﮕ"},{"id":50418,"position":4,"audio_url":"wbw/043_053_004.mp3","verse_key":"43:53","verse_id":4378,"location":"43:53:4","code_v1":"ﮖ","char_type_name":"word","page_number":493,"line_number":7,"text":"ﮖ"},{"id":50419,"position":5,"audio_url":"wbw/043_053_005.mp3","verse_key":"43:53","verse_id":4378,"location":"43:53:5","code_v1":"ﮗ","char_type_name":"word","page_number":493,"line_number":7,"text":"ﮗ"},{"id":50420,"position":6,"audio_url":"wbw/043_053_006.mp3","verse_key":"43:53","verse_id":4378,"location":"43:53:6","code_v1":"ﮘ","char_type_name":"word","page_number":493,"line_number":7,"text":"ﮘ"},{"id":50421,"position":7,"audio_url":"wbw/043_053_007.mp3","verse_key":"43:53","verse_id":4378,"location":"43:53:7","code_v1":"ﮙ","char_type_name":"word","page_number":493,"line_number":7,"text":"ﮙ"},{"id":50422,"position":8,"audio_url":"wbw/043_053_008.mp3","verse_key":"43:53","verse_id":4378,"location":"43:53:8","code_v1":"ﮚ","char_type_name":"word","page_number":493,"line_number":7,"text":"ﮚ"},{"id":50423,"position":9,"audio_url":"wbw/043_053_009.mp3","verse_key":"43:53","verse_id":4378,"location":"43:53:9","code_v1":"ﮛ","char_type_name":"word","page_number":493,"line_number":8,"text":"ﮛ"},{"id":50424,"position":10,"audio_url":"wbw/043_053_010.mp3","verse_key":"43:53","verse_id":4378,"location":"43:53:10","code_v1":"ﮜ","char_type_name":"word","page_number":493,"line_number":8,"text":"ﮜ"},{"id":50425,"position":11,"audio_url":"wbw/043_053_011.mp3","verse_key":"43:53","verse_id":4378,"location":"43:53:11","code_v1":"ﮝ","char_type_name":"word","page_number":493,"line_number":8,"text":"ﮝ"},{"id":50426,"position":12,"audio_url":null,"verse_key":"43:53","verse_id":4378,"location":"43:53:12","code_v1":"ﮞ","char_type_name":"end","page_number":493,"line_number":8,"text":"ﮞ"}]}, {"id":4379,"verse_number":54,"verse_key":"43:54","hizb_number":50,"rub_el_hizb_number":197,"ruku_number":430,"manzil_number":6,"sajdah_number":null,"text_imlaei_simple":"فاستخف قومه فاطاعوه انهم كانوا قوما فاسقين","page_number":493,"juz_number":25,"words":[{"id":51235,"position":1,"audio_url":"wbw/043_054_001.mp3","verse_key":"43:54","verse_id":4379,"location":"43:54:1","code_v1":"ﮟ","char_type_name":"word","page_number":493,"line_number":8,"text":"ﮟ"},{"id":51236,"position":2,"audio_url":"wbw/043_054_002.mp3","verse_key":"43:54","verse_id":4379,"location":"43:54:2","code_v1":"ﮠ","char_type_name":"word","page_number":493,"line_number":8,"text":"ﮠ"},{"id":51237,"position":3,"audio_url":"wbw/043_054_003.mp3","verse_key":"43:54","verse_id":4379,"location":"43:54:3","code_v1":"ﮡﮢ","char_type_name":"word","page_number":493,"line_number":9,"text":"ﮡﮢ"},{"id":51239,"position":4,"audio_url":"wbw/043_054_005.mp3","verse_key":"43:54","verse_id":4379,"location":"43:54:4","code_v1":"ﮣ","char_type_name":"word","page_number":493,"line_number":9,"text":"ﮣ"},{"id":51240,"position":5,"audio_url":"wbw/043_054_006.mp3","verse_key":"43:54","verse_id":4379,"location":"43:54:5","code_v1":"ﮤ","char_type_name":"word","page_number":493,"line_number":9,"text":"ﮤ"},{"id":51241,"position":6,"audio_url":"wbw/043_054_007.mp3","verse_key":"43:54","verse_id":4379,"location":"43:54:6","code_v1":"ﮥ","char_type_name":"word","page_number":493,"line_number":9,"text":"ﮥ"},{"id":51242,"position":7,"audio_url":"wbw/043_054_008.mp3","verse_key":"43:54","verse_id":4379,"location":"43:54:7","code_v1":"ﮦ","char_type_name":"word","page_number":493,"line_number":9,"text":"ﮦ"},{"id":51243,"position":8,"audio_url":null,"verse_key":"43:54","verse_id":4379,"location":"43:54:8","code_v1":"ﮧ","char_type_name":"end","page_number":493,"line_number":9,"text":"ﮧ"}]}, {"id":4380,"verse_number":55,"verse_key":"43:55","hizb_number":50,"rub_el_hizb_number":197,"ruku_number":430,"manzil_number":6,"sajdah_number":null,"text_imlaei_simple":"فلما اسفونا انتقمنا منهم فاغرقناهم اجمعين","page_number":493,"juz_number":25,"words":[{"id":51582,"position":1,"audio_url":"wbw/043_055_001.mp3","verse_key":"43:55","verse_id":4380,"location":"43:55:1","code_v1":"ﮨ","char_type_name":"word","page_number":493,"line_number":9,"text":"ﮨ"},{"id":51583,"position":2,"audio_url":"wbw/043_055_002.mp3","verse_key":"43:55","verse_id":4380,"location":"43:55:2","code_v1":"ﮩ","char_type_name":"word","page_number":493,"line_number":9,"text":"ﮩ"},{"id":51584,"position":3,"audio_url":"wbw/043_055_003.mp3","verse_key":"43:55","verse_id":4380,"location":"43:55:3","code_v1":"ﮪ","char_type_name":"word","page_number":493,"line_number":10,"text":"ﮪ"},{"id":51585,"position":4,"audio_url":"wbw/043_055_004.mp3","verse_key":"43:55","verse_id":4380,"location":"43:55:4","code_v1":"ﮫ","char_type_name":"word","page_number":493,"line_number":10,"text":"ﮫ"},{"id":51586,"position":5,"audio_url":"wbw/043_055_005.mp3","verse_key":"43:55","verse_id":4380,"location":"43:55:5","code_v1":"ﮬ","char_type_name":"word","page_number":493,"line_number":10,"text":"ﮬ"},{"id":51587,"position":6,"audio_url":"wbw/043_055_006.mp3","verse_key":"43:55","verse_id":4380,"location":"43:55:6","code_v1":"ﮭ","char_type_name":"word","page_number":493,"line_number":10,"text":"ﮭ"},{"id":51588,"position":7,"audio_url":null,"verse_key":"43:55","verse_id":4380,"location":"43:55:7","code_v1":"ﮮ","char_type_name":"end","page_number":493,"line_number":10,"text":"ﮮ"}]}, {"id":4381,"verse_number":56,"verse_key":"43:56","hizb_number":50,"rub_el_hizb_number":197,"ruku_number":430,"manzil_number":6,"sajdah_number":null,"text_imlaei_simple":"فجعلناهم سلفا ومثلا للاخرين","page_number":493,"juz_number":25,"words":[{"id":52132,"position":1,"audio_url":"wbw/043_056_001.mp3","verse_key":"43:56","verse_id":4381,"location":"43:56:1","code_v1":"ﮯ","char_type_name":"word","page_number":493,"line_number":10,"text":"ﮯ"},{"id":52133,"position":2,"audio_url":"wbw/043_056_002.mp3","verse_key":"43:56","verse_id":4381,"location":"43:56:2","code_v1":"ﮰ","char_type_name":"word","page_number":493,"line_number":11,"text":"ﮰ"},{"id":52134,"position":3,"audio_url":"wbw/043_056_003.mp3","verse_key":"43:56","verse_id":4381,"location":"43:56:3","code_v1":"ﮱ","char_type_name":"word","page_number":493,"line_number":11,"text":"ﮱ"},{"id":52135,"position":4,"audio_url":"wbw/043_056_004.mp3","verse_key":"43:56","verse_id":4381,"location":"43:56:4","code_v1":"ﯓ","char_type_name":"word","page_number":493,"line_number":11,"text":"ﯓ"},{"id":52136,"position":5,"audio_url":null,"verse_key":"43:56","verse_id":4381,"location":"43:56:5","code_v1":"ﯔ","char_type_name":"end","page_number":493,"line_number":11,"text":"ﯔ"}]}, {"id":4382,"verse_number":57,"verse_key":"43:57","hizb_number":50,"rub_el_hizb_number":198,"ruku_number":431,"manzil_number":6,"sajdah_number":null,"text_imlaei_simple":"ولما ضرب ابن مريم مثلا اذا قومك منه يصدون","page_number":493,"juz_number":25,"words":[{"id":52680,"position":1,"audio_url":"wbw/043_057_002.mp3","verse_key":"43:57","verse_id":4382,"location":"43:57:1","code_v1":"ﯕ ﯖ","char_type_name":"word","page_number":493,"line_number":11,"text":"ﯕ ﯖ"},{"id":52681,"position":2,"audio_url":"wbw/043_057_003.mp3","verse_key":"43:57","verse_id":4382,"location":"43:57:2","code_v1":"ﯗ","char_type_name":"word","page_number":493,"line_number":11,"text":"ﯗ"},{"id":52682,"position":3,"audio_url":"wbw/043_057_004.mp3","verse_key":"43:57","verse_id":4382,"location":"43:57:3","code_v1":"ﯘ","char_type_name":"word","page_number":493,"line_number":11,"text":"ﯘ"},{"id":52683,"position":4,"audio_url":"wbw/043_057_005.mp3","verse_key":"43:57","verse_id":4382,"location":"43:57:4","code_v1":"ﯙ","char_type_name":"word","page_number":493,"line_number":11,"text":"ﯙ"},{"id":52684,"position":5,"audio_url":"wbw/043_057_006.mp3","verse_key":"43:57","verse_id":4382,"location":"43:57:5","code_v1":"ﯚ","char_type_name":"word","page_number":493,"line_number":12,"text":"ﯚ"},{"id":52685,"position":6,"audio_url":"wbw/043_057_007.mp3","verse_key":"43:57","verse_id":4382,"location":"43:57:6","code_v1":"ﯛ","char_type_name":"word","page_number":493,"line_number":12,"text":"ﯛ"},{"id":52686,"position":7,"audio_url":"wbw/043_057_008.mp3","verse_key":"43:57","verse_id":4382,"location":"43:57:7","code_v1":"ﯜ","char_type_name":"word","page_number":493,"line_number":12,"text":"ﯜ"},{"id":52687,"position":8,"audio_url":"wbw/043_057_009.mp3","verse_key":"43:57","verse_id":4382,"location":"43:57:8","code_v1":"ﯝ","char_type_name":"word","page_number":493,"line_number":12,"text":"ﯝ"},{"id":52688,"position":9,"audio_url":"wbw/043_057_010.mp3","verse_key":"43:57","verse_id":4382,"location":"43:57:9","code_v1":"ﯞ","char_type_name":"word","page_number":493,"line_number":12,"text":"ﯞ"},{"id":52689,"position":10,"audio_url":null,"verse_key":"43:57","verse_id":4382,"location":"43:57:10","code_v1":"ﯟ","char_type_name":"end","page_number":493,"line_number":12,"text":"ﯟ"}]}, {"id":4383,"verse_number":58,"verse_key":"43:58","hizb_number":50,"rub_el_hizb_number":198,"ruku_number":431,"manzil_number":6,"sajdah_number":null,"text_imlaei_simple":"وقالوا االهتنا خير ام هو ما ضربوه لك الا جدلا بل هم قوم خصمون","page_number":493,"juz_number":25,"words":[{"id":53275,"position":1,"audio_url":"wbw/043_058_001.mp3","verse_key":"43:58","verse_id":4383,"location":"43:58:1","code_v1":"ﯠ","char_type_name":"word","page_number":493,"line_number":12,"text":"ﯠ"},{"id":53276,"position":2,"audio_url":"wbw/043_058_002.mp3","verse_key":"43:58","verse_id":4383,"location":"43:58:2","code_v1":"ﯡ","char_type_name":"word","page_number":493,"line_number":12,"text":"ﯡ"},{"id":53277,"position":3,"audio_url":"wbw/043_058_003.mp3","verse_key":"43:58","verse_id":4383,"location":"43:58:3","code_v1":"ﯢ","char_type_name":"word","page_number":493,"line_number":13,"text":"ﯢ"},{"id":53278,"position":4,"audio_url":"wbw/043_058_004.mp3","verse_key":"43:58","verse_id":4383,"location":"43:58:4","code_v1":"ﯣ","char_type_name":"word","page_number":493,"line_number":13,"text":"ﯣ"},{"id":53279,"position":5,"audio_url":"wbw/043_058_005.mp3","verse_key":"43:58","verse_id":4383,"location":"43:58:5","code_v1":"ﯤﯥ","char_type_name":"word","page_number":493,"line_number":13,"text":"ﯤﯥ"},{"id":53281,"position":6,"audio_url":"wbw/043_058_007.mp3","verse_key":"43:58","verse_id":4383,"location":"43:58:6","code_v1":"ﯦ","char_type_name":"word","page_number":493,"line_number":13,"text":"ﯦ"},{"id":53282,"position":7,"audio_url":"wbw/043_058_008.mp3","verse_key":"43:58","verse_id":4383,"location":"43:58:7","code_v1":"ﯧ","char_type_name":"word","page_number":493,"line_number":13,"text":"ﯧ"},{"id":53283,"position":8,"audio_url":"wbw/043_058_009.mp3","verse_key":"43:58","verse_id":4383,"location":"43:58:8","code_v1":"ﯨ","char_type_name":"word","page_number":493,"line_number":13,"text":"ﯨ"},{"id":53284,"position":9,"audio_url":"wbw/043_058_010.mp3","verse_key":"43:58","verse_id":4383,"location":"43:58:9","code_v1":"ﯩ","char_type_name":"word","page_number":493,"line_number":13,"text":"ﯩ"},{"id":53285,"position":10,"audio_url":"wbw/043_058_011.mp3","verse_key":"43:58","verse_id":4383,"location":"43:58:10","code_v1":"ﯪﯫ","char_type_name":"word","page_number":493,"line_number":13,"text":"ﯪﯫ"},{"id":53287,"position":11,"audio_url":"wbw/043_058_013.mp3","verse_key":"43:58","verse_id":4383,"location":"43:58:11","code_v1":"ﯬ","char_type_name":"word","page_number":493,"line_number":13,"text":"ﯬ"},{"id":53288,"position":12,"audio_url":"wbw/043_058_014.mp3","verse_key":"43:58","verse_id":4383,"location":"43:58:12","code_v1":"ﯭ","char_type_name":"word","page_number":493,"line_number":13,"text":"ﯭ"},{"id":53289,"position":13,"audio_url":"wbw/043_058_015.mp3","verse_key":"43:58","verse_id":4383,"location":"43:58:13","code_v1":"ﯮ","char_type_name":"word","page_number":493,"line_number":13,"text":"ﯮ"},{"id":53290,"position":14,"audio_url":"wbw/043_058_016.mp3","verse_key":"43:58","verse_id":4383,"location":"43:58:14","code_v1":"ﯯ","char_type_name":"word","page_number":493,"line_number":13,"text":"ﯯ"},{"id":53291,"position":15,"audio_url":null,"verse_key":"43:58","verse_id":4383,"location":"43:58:15","code_v1":"ﯰ","char_type_name":"end","page_number":493,"line_number":13,"text":"ﯰ"}]}, {"id":4384,"verse_number":59,"verse_key":"43:59","hizb_number":50,"rub_el_hizb_number":198,"ruku_number":431,"manzil_number":6,"sajdah_number":null,"text_imlaei_simple":"ان هو الا عبد انعمنا عليه وجعلناه مثلا لبني اسرائيل","page_number":493,"juz_number":25,"words":[{"id":53699,"position":1,"audio_url":"wbw/043_059_001.mp3","verse_key":"43:59","verse_id":4384,"location":"43:59:1","code_v1":"ﯱ","char_type_name":"word","page_number":493,"line_number":14,"text":"ﯱ"},{"id":53700,"position":2,"audio_url":"wbw/043_059_002.mp3","verse_key":"43:59","verse_id":4384,"location":"43:59:2","code_v1":"ﯲ","char_type_name":"word","page_number":493,"line_number":14,"text":"ﯲ"},{"id":53701,"position":3,"audio_url":"wbw/043_059_003.mp3","verse_key":"43:59","verse_id":4384,"location":"43:59:3","code_v1":"ﯳ","char_type_name":"word","page_number":493,"line_number":14,"text":"ﯳ"},{"id":53702,"position":4,"audio_url":"wbw/043_059_004.mp3","verse_key":"43:59","verse_id":4384,"location":"43:59:4","code_v1":"ﯴ","char_type_name":"word","page_number":493,"line_number":14,"text":"ﯴ"},{"id":53703,"position":5,"audio_url":"wbw/043_059_005.mp3","verse_key":"43:59","verse_id":4384,"location":"43:59:5","code_v1":"ﯵ","char_type_name":"word","page_number":493,"line_number":14,"text":"ﯵ"},{"id":53704,"position":6,"audio_url":"wbw/043_059_006.mp3","verse_key":"43:59","verse_id":4384,"location":"43:59:6","code_v1":"ﯶ","char_type_name":"word","page_number":493,"line_number":14,"text":"ﯶ"},{"id":53705,"position":7,"audio_url":"wbw/043_059_007.mp3","verse_key":"43:59","verse_id":4384,"location":"43:59:7","code_v1":"ﯷ","char_type_name":"word","page_number":493,"line_number":14,"text":"ﯷ"},{"id":53706,"position":8,"audio_url":"wbw/043_059_008.mp3","verse_key":"43:59","verse_id":4384,"location":"43:59:8","code_v1":"ﯸ","char_type_name":"word","page_number":493,"line_number":14,"text":"ﯸ"},{"id":53707,"position":9,"audio_url":"wbw/043_059_009.mp3","verse_key":"43:59","verse_id":4384,"location":"43:59:9","code_v1":"ﯹ","char_type_name":"word","page_number":493,"line_number":14,"text":"ﯹ"},{"id":53708,"position":10,"audio_url":"wbw/043_059_010.mp3","verse_key":"43:59","verse_id":4384,"location":"43:59:10","code_v1":"ﯺ","char_type_name":"word","page_number":493,"line_number":14,"text":"ﯺ"},{"id":53709,"position":11,"audio_url":null,"verse_key":"43:59","verse_id":4384,"location":"43:59:11","code_v1":"ﯻ","char_type_name":"end","page_number":493,"line_number":15,"text":"ﯻ"}]}, {"id":4385,"verse_number":60,"verse_key":"43:60","hizb_number":50,"rub_el_hizb_number":198,"ruku_number":431,"manzil_number":6,"sajdah_number":null,"text_imlaei_simple":"ولو نشاء لجعلنا منكم ملائكة في الارض يخلفون","page_number":493,"juz_number":25,"words":[{"id":54430,"position":1,"audio_url":"wbw/043_060_001.mp3","verse_key":"43:60","verse_id":4385,"location":"43:60:1","code_v1":"ﯼ","char_type_name":"word","page_number":493,"line_number":15,"text":"ﯼ"},{"id":54431,"position":2,"audio_url":"wbw/043_060_002.mp3","verse_key":"43:60","verse_id":4385,"location":"43:60:2","code_v1":"ﯽ","char_type_name":"word","page_number":493,"line_number":15,"text":"ﯽ"},{"id":54432,"position":3,"audio_url":"wbw/043_060_003.mp3","verse_key":"43:60","verse_id":4385,"location":"43:60:3","code_v1":"ﯾ","char_type_name":"word","page_number":493,"line_number":15,"text":"ﯾ"},{"id":54433,"position":4,"audio_url":"wbw/043_060_004.mp3","verse_key":"43:60","verse_id":4385,"location":"43:60:4","code_v1":"ﯿ","char_type_name":"word","page_number":493,"line_number":15,"text":"ﯿ"},{"id":54434,"position":5,"audio_url":"wbw/043_060_005.mp3","verse_key":"43:60","verse_id":4385,"location":"43:60:5","code_v1":"ﰀ","char_type_name":"word","page_number":493,"line_number":15,"text":"ﰀ"},{"id":54435,"position":6,"audio_url":"wbw/043_060_006.mp3","verse_key":"43:60","verse_id":4385,"location":"43:60:6","code_v1":"ﰁ","char_type_name":"word","page_number":493,"line_number":15,"text":"ﰁ"},{"id":54436,"position":7,"audio_url":"wbw/043_060_007.mp3","verse_key":"43:60","verse_id":4385,"location":"43:60:7","code_v1":"ﰂ","char_type_name":"word","page_number":493,"line_number":15,"text":"ﰂ"},{"id":54437,"position":8,"audio_url":"wbw/043_060_008.mp3","verse_key":"43:60","verse_id":4385,"location":"43:60:8","code_v1":"ﰃ","char_type_name":"word","page_number":493,"line_number":15,"text":"ﰃ"},{"id":54438,"position":9,"audio_url":null,"verse_key":"43:60","verse_id":4385,"location":"43:60:9","code_v1":"ﰄ","char_type_name":"end","page_number":493,"line_number":15,"text":"ﰄ"}]}]